rabibridge/__init__.py
rabibridge/exceptions.py
rabibridge/models.py
rabibridge/mq.py
rabibridge/permissions.py
rabibridge/serialisation.py
rabibridge/utils.py
RabiBridge-0.1.2.dist-info/LICENSE
RabiBridge-0.1.2.dist-info/METADATA
RabiBridge-0.1.2.dist-info/WHEEL
RabiBridge-0.1.2.dist-info/top_level.txt
RabiBridge-0.1.2.dist-info/RECORD
