Metadata-Version: 2.1
Name: RabiBridge
Version: 0.1.2
Summary: A lightweight framework for service decoupling and peak shaving in web services, leveraging RabbitMQ. - GoodManWEN/RabiBridge
Home-page: https://github.com/GoodManWEN/RabiBridge
Author: WEN
Keywords: RabiBridge,rabbitmq,rpc,fastapi
Classifier: Programming Language :: Python :: 3
Classifier: Programming Language :: Python :: 3.8
Classifier: Programming Language :: Python :: 3.9
Classifier: Programming Language :: Python :: 3.10
Classifier: Programming Language :: Python :: 3.11
Classifier: Programming Language :: Python :: 3.12
Classifier: License :: OSI Approved :: MIT License
Classifier: Operating System :: POSIX :: Linux
Classifier: Operating System :: Microsoft :: Windows
Requires-Python: >=3.8
License-File: LICENSE
Requires-Dist: uvicorn
Requires-Dist: fastapi
Requires-Dist: zstandard
Requires-Dist: aio-pika
Requires-Dist: psutil
Requires-Dist: loguru
Requires-Dist: uvloop
Requires-Dist: pipeit
Requires-Dist: toml
Requires-Dist: cryptography
Requires-Dist: msgpack
